rdfx/__init__.py
rdfx/clean_ttl.py
rdfx/floods.ttl
rdfx/persistence_systems.py
rdfx/rdfx_cli.py
rdfx/test.ttl
rdfx/testbackup.ttl
rdfx-0.4.18.dist-info/entry_points.txt
rdfx-0.4.18.dist-info/LICENSE
rdfx-0.4.18.dist-info/WHEEL
rdfx-0.4.18.dist-info/METADATA
rdfx-0.4.18.dist-info/RECORD
