Metadata-Version: 2.1
Name: rdfx
Version: 0.4.18
Summary: Tools for converting, merging, persisting and reading RDF data in different formats.
Home-page: https://github.com/surroundaustralia/rdfx
License: BSD-3-Clause
Keywords: RDF,Linked Data,Turtle,N-Triples,Semantic Web,RDFLib
Author: david-habgood
Author-email: david.habgood@surroundaustralia.com
Maintainer: adam-davis
Maintainer-email: adam.davis@surroundaustralia.com
Requires-Python: >=3.8,<4.0
Classifier: License :: OSI Approved :: BSD License
Classifier: Programming Language :: Python :: 3
Classifier: Programming Language :: Python :: 3.8
Classifier: Programming Language :: Python :: 3.9
Classifier: Programming Language :: Python :: 3.10
Classifier: Programming Language :: Python :: 3.11
Provides-Extra: app
Requires-Dist: boto3 (>=1.20.20,<2.0.0)
Requires-Dist: httpx (>=0.23.0,<0.24.0)
Requires-Dist: python-dotenv (>=0.19.2,<0.20.0); extra == "app"
Requires-Dist: rdflib (>=6.0.2,<7.0.0)
Requires-Dist: requests (>=2.26.0,<3.0.0)
Requires-Dist: streamlit (>=1.2.0,<2.0.0); extra == "app"
Project-URL: Repository, https://github.com/surroundaustralia/rdfx
